MANIFEST.in
README.txt
blacklist-3.3.x.cfg
setup.py
whitelist-3.3.x.cfg
doc/Makefile
doc/api.rst
doc/changes.rst
doc/conf.py
doc/contact.rst
doc/extensions.rst
doc/index.rst
doc/introduction.rst
doc/make.bat
doc/quickstart.rst
doc/usage.rst
doc/_build/doctrees/api.doctree
doc/_build/doctrees/changes.doctree
doc/_build/doctrees/contact.doctree
doc/_build/doctrees/environment.pickle
doc/_build/doctrees/extensions.doctree
doc/_build/doctrees/index.doctree
doc/_build/doctrees/introduction.doctree
doc/_build/doctrees/quickstart.doctree
doc/_build/doctrees/usage.doctree
doc/_build/html/.buildinfo
doc/_build/html/api.html
doc/_build/html/changes.html
doc/_build/html/contact.html
doc/_build/html/extensions.html
doc/_build/html/genindex.html
doc/_build/html/index.html
doc/_build/html/introduction.html
doc/_build/html/objects.inv
doc/_build/html/quickstart.html
doc/_build/html/search.html
doc/_build/html/searchindex.js
doc/_build/html/usage.html
doc/_build/html/_sources/api.txt
doc/_build/html/_sources/changes.txt
doc/_build/html/_sources/contact.txt
doc/_build/html/_sources/extensions.txt
doc/_build/html/_sources/index.txt
doc/_build/html/_sources/introduction.txt
doc/_build/html/_sources/quickstart.txt
doc/_build/html/_sources/usage.txt
doc/_build/html/_static/basic.css
doc/_build/html/_static/default.css
doc/_build/html/_static/doctools.js
doc/_build/html/_static/file.png
doc/_build/html/_static/jquery.js
doc/_build/html/_static/minus.png
doc/_build/html/_static/plus.png
doc/_build/html/_static/pygments.css
doc/_build/html/_static/searchtools.js
doc/_build/html/_static/sidebar.js
doc/_build/html/_static/underscore.js
wsapi4plone/__init__.py
wsapi4plone.core.egg-info/PKG-INFO
wsapi4plone.core.egg-info/SOURCES.txt
wsapi4plone.core.egg-info/dependency_links.txt
wsapi4plone.core.egg-info/entry_points.txt
wsapi4plone.core.egg-info/namespace_packages.txt
wsapi4plone.core.egg-info/not-zip-safe
wsapi4plone.core.egg-info/requires.txt
wsapi4plone.core.egg-info/top_level.txt
wsapi4plone/core/__init__.py
wsapi4plone/core/configure.zcml
wsapi4plone/core/exceptions.py
wsapi4plone/core/extension.py
wsapi4plone/core/interfaces.py
wsapi4plone/core/permissions.zcml
wsapi4plone/core/profiles.zcml
wsapi4plone/core/service.py
wsapi4plone/core/service.txt
wsapi4plone/core/setuphandlers.py
wsapi4plone/core/version.txt
