Metadata-Version: 1.0
Name: wsapi4plone.core
Version: 0.2
Summary: A Web Services API for Plone (>=3.x).
Home-page: http://packages.python.org/wsapi4plone.core/
Author: WebLion Group, Penn State University
Author-email: support@weblion.psu.edu
License: GPL
Keywords: wsapi api xmlrpc weblion
Platform: UNKNOWN
Classifier: Framework :: Plone
Classifier: Framework :: Zope2
Classifier: Programming Language :: Python
Classifier: Topic :: Software Development :: Libraries :: Python Modules
Classifier: Intended Audience :: Developers
Classifier: Development Status :: 5 - Production/Stable
